easy_dotenv/__init__.py
easy_dotenv/exceptions.py
easy_dotenv/loader.py
easy_dotenv/types.py
easy_dotenv-0.3.2.dist-info/LICENSE
easy_dotenv-0.3.2.dist-info/METADATA
easy_dotenv-0.3.2.dist-info/WHEEL
easy_dotenv-0.3.2.dist-info/top_level.txt
easy_dotenv-0.3.2.dist-info/RECORD
