Metadata-Version: 2.2
Name: easy-dotenv
Version: 0.3.2
Summary: Simple and type-safe environment variables management for Python
Author-email: Ilya <ilya.pugachev@icloud.com>
License: MIT
Project-URL: Homepage, https://github.com/EliPug/easy-dotenv
Project-URL: Repository, https://github.com/EliPug/easy-dotenv
Project-URL: Documentation, https://github.com/EliPug/easy-dotenv/blob/main/README.md
Classifier: Programming Language :: Python :: 3
Classifier: Programming Language :: Python :: 3.7
Classifier: Programming Language :: Python :: 3.8
Classifier: Programming Language :: Python :: 3.9
Classifier: Programming Language :: Python :: 3.10
Classifier: Programming Language :: Python :: 3.11
Classifier: License :: OSI Approved :: MIT License
Classifier: Operating System :: OS Independent
Classifier: Intended Audience :: Developers
Classifier: Topic :: Software Development :: Libraries :: Python Modules
Classifier: Development Status :: 4 - Beta
Requires-Python: >=3.7
License-File: LICENSE
Requires-Dist: python-dotenv>=0.19.0
Provides-Extra: dev
Requires-Dist: pytest>=7.0.0; extra == "dev"
Requires-Dist: pytest-cov>=4.0.0; extra == "dev"
